gf_api_client/__init__.py
gf_api_client/client.py
gf_api_client/conditions.py
gf_api_client-0.1.3.dist-info/LICENSE
gf_api_client-0.1.3.dist-info/METADATA
gf_api_client-0.1.3.dist-info/WHEEL
gf_api_client-0.1.3.dist-info/top_level.txt
gf_api_client-0.1.3.dist-info/RECORD
